magpylib/__init__.py
magpylib/_version.py
magpylib/_version.pyi
magpylib/py.typed
magpylib/_src/__init__.py
magpylib/_src/exceptions.py
magpylib/_src/input_checks.py
magpylib/_src/style.py
magpylib/_src/utility.py
magpylib/_src/defaults/__init__.py
magpylib/_src/defaults/defaults_classes.py
magpylib/_src/defaults/defaults_utility.py
magpylib/_src/defaults/defaults_values.py
magpylib/_src/display/__init__.py
magpylib/_src/display/backend_matplotlib.py
magpylib/_src/display/backend_plotly.py
magpylib/_src/display/backend_pyvista.py
magpylib/_src/display/display.py
magpylib/_src/display/sensor_mesh.py
magpylib/_src/display/traces_base.py
magpylib/_src/display/traces_core.py
magpylib/_src/display/traces_generic.py
magpylib/_src/display/traces_utility.py
magpylib/_src/fields/__init__.py
magpylib/_src/fields/field_BH.py
magpylib/_src/fields/field_BH_circle.py
magpylib/_src/fields/field_BH_cuboid.py
magpylib/_src/fields/field_BH_current_sheet.py
magpylib/_src/fields/field_BH_cylinder.py
magpylib/_src/fields/field_BH_cylinder_segment.py
magpylib/_src/fields/field_BH_dipole.py
magpylib/_src/fields/field_BH_polyline.py
magpylib/_src/fields/field_BH_sphere.py
magpylib/_src/fields/field_BH_tetrahedron.py
magpylib/_src/fields/field_BH_triangle.py
magpylib/_src/fields/field_BH_triangularmesh.py
magpylib/_src/fields/field_BHfunc.py
magpylib/_src/fields/field_FT.py
magpylib/_src/fields/special_cel.py
magpylib/_src/fields/special_el3.py
magpylib/_src/obj_classes/__init__.py
magpylib/_src/obj_classes/class_BaseDisplayRepr.py
magpylib/_src/obj_classes/class_BaseExcitations.py
magpylib/_src/obj_classes/class_BaseGeo.py
magpylib/_src/obj_classes/class_BasePropDipole.py
magpylib/_src/obj_classes/class_BasePropVolume.py
magpylib/_src/obj_classes/class_BaseProperties.py
magpylib/_src/obj_classes/class_BaseTarget.py
magpylib/_src/obj_classes/class_BaseTransform.py
magpylib/_src/obj_classes/class_Collection.py
magpylib/_src/obj_classes/class_Sensor.py
magpylib-5.2.1.dist-info/METADATA
magpylib-5.2.1.dist-info/WHEEL
magpylib-5.2.1.dist-info/licenses/LICENSE
magpylib-5.2.1.dist-info/RECORD
