Metadata-Version: 2.4
Name: magpylib
Version: 5.2.1
Summary: Python package for computation of magnetic fields of magnets, currents and moments.
Project-URL: Homepage, https://github.com/magpylib/magpylib
Project-URL: Bug Tracker, https://github.com/magpylib/magpylib/issues
Project-URL: Discussions, https://github.com/magpylib/magpylib/discussions
Project-URL: Changelog, https://github.com/magpylib/magpylib/releases
Author-email: Michael Ortner <magpylib@gmail.com>
Maintainer-email: Alexandre Boisselet <alexabois+magpylib@gmail.com>
License: Copyright (c) 2022, Silicon Austria Labs, Magpylib Developers.
License-File: LICENSE
Keywords: B-field,analytical,electromagnetic,magnetic-field,magnetism,physics
Classifier: Development Status :: 1 - Planning
Classifier: Intended Audience :: Developers
Classifier: Intended Audience :: Science/Research
Classifier: License :: OSI Approved :: BSD License
Classifier: Operating System :: OS Independent
Classifier: Programming Language :: Python
Classifier: Programming Language :: Python :: 3
Classifier: Programming Language :: Python :: 3 :: Only
Classifier: Programming Language :: Python :: 3.11
Classifier: Programming Language :: Python :: 3.12
Classifier: Programming Language :: Python :: 3.13
Classifier: Topic :: Scientific/Engineering
Classifier: Typing :: Typed
Requires-Python: >=3.11
Requires-Dist: matplotlib>=3.6
Requires-Dist: numpy>=1.23
Requires-Dist: plotly>=5.16
Requires-Dist: scipy>=1.8
